MeasureSuiteCommandLine/__init__.py
MeasureSuiteCommandLine/helper.py
MeasureSuiteCommandLine/ms.py
MeasureSuiteCommandLine/test/__init__.py
MeasureSuiteCommandLine/test/test_ms.py
measuresuitecommandline-0.3.0.dist-info/licenses/LICENSE
measuresuitecommandline-0.3.0.dist-info/METADATA
measuresuitecommandline-0.3.0.dist-info/WHEEL
measuresuitecommandline-0.3.0.dist-info/entry_points.txt
measuresuitecommandline-0.3.0.dist-info/top_level.txt
measuresuitecommandline-0.3.0.dist-info/RECORD
