Metadata-Version: 2.4
Name: MeasureSuiteCommandLine
Version: 0.3.0
Summary: Measure Code
Author-email: FloydZ <floyd.zweydinger+github@rub.de>
Maintainer-email: FloydZ <floyd.zweydinger+github@rub.de>
Project-URL: Repository, https://github.com/FloydZ/MeasureSuiteCommandLine
Keywords: MeasureSuite,Measure
Classifier: Programming Language :: Python :: 3
Classifier: Development Status :: 4 - Beta
Requires-Python: >=3.8
License-File: LICENSE
Requires-Dist: pycparser
Dynamic: license-file
